{
  "dct_title_s": "General Land Office Township Plat - Original Survey: Minnesota (T110N R26W), 1855",
  "dct_alternative_sm": [
    "Original Public Land Survey"
  ],
  "dct_description_sm": [
    "Same as map ID1589, but unsigned and missing meanders"
  ],
  "dct_language_sm": [
    "eng"
  ],
  "dct_publisher_sm": [
    "Minnesota Geospatial Information Office (MnGeo)"
  ],
  "schema_provider_s": "University of Minnesota",
  "gbl_resourceClass_sm": [
    "Maps"
  ],
  "gbl_resourceType_sm": [
    "Cadastral maps"
  ],
  "dct_subject_sm": [
    "Surveying--Public lands"
  ],
  "dcat_keyword_sm": [
    "land survey",
    "surveyor",
    "public land survey system",
    "PLSS",
    "pls"
  ],
  "dct_temporal_sm": [
    "1855"
  ],
  "dct_issued_s": "1855",
  "gbl_indexYear_im": [
    "1855"
  ],
  "gbl_dateRange_drsim": [
    "[1855 TO 1855]"
  ],
  "dct_spatial_sm": [
    " Minnesota--Nicollet County",
    "T110N-R026W"
  ],
  "locn_geometry": "POLYGON((-94.00960559 44.37004124, -93.88875989 44.37004124, -93.88875989 44.28289072, -94.00960559 44.28289072, -94.00960559 44.37004124))",
  "dcat_bbox": "ENVELOPE(-94.00960559,-93.88875989,44.37004124,44.28289072)",
  "dcat_centroid": "44.326465979999995,-93.94918274",
  "dct_relation_sm": [
    "8888-003"
  ],
  "pcdm_memberOf_sm": [
    "77f-0001"
  ],
  "dct_accessRights_s": "Public",
  "dct_format_s": "GeoJPEG",
  "dct_references_s": "{\"http://schema.org/downloadUrl\":\"https://resources.gisdata.mn.gov/pub/data/basemaps/glo/Nicollet/Georeferenced/t110r26w5fi01.zip\",\"http://www.w3.org/1999/xhtml\":\"https://resources.gisdata.mn.gov/pub/gdrs/data/pub/us_mn_state_mngeo/plan_glo_plat_maps_georef/metadata/metadata.html\",\"http://schema.org/url\":\"http://www.mngeo.state.mn.us/glo/glo.php?township=110\\u0026range=26\"}",
  "id": "t110r26w5fi01",
  "dct_identifier_sm": [
    "t110r26w5fi01",
    "MN-T110N-R026W"
  ],
  "gbl_mdVersion_s": "Aardvark"
}