{
  "dct_title_s": "Map of British Guiana : from the latest surveys of Schomburgk, Owen, Hilhouse, & others ; & those of Hancock, Van-Cooten, Bouchenroeder, & Bercheyck ...",
  "dct_description_sm": [
    "Relief shown by hachures.; Hand col. shows cultivated and previously cultivated lands; shows also pariochial divisions, etc.; \"Respectfully dedicated to His Excellency Henry Light Esqr., Governor ... by His Excellency's very obedient, humble servant J. Hadfield, Crown Surveyor ...\"",
    "41 x 44 centimeters",
    "Scale approximately 1:1,520,640",
    "General Map Collection"
  ],
  "dct_language_sm": [
    "eng"
  ],
  "dct_creator_sm": [
    "Hadfield, J. (Joseph)"
  ],
  "dct_publisher_sm": [
    "John Arrowsmith (London)"
  ],
  "schema_provider_s": "University of Minnesota",
  "gbl_resourceClass_sm": [
    "Maps"
  ],
  "dct_temporal_sm": [
    "1839"
  ],
  "dct_issued_s": "1839",
  "dct_spatial_sm": [
    "French Guiana"
  ],
  "locn_geometry": "POLYGON((-61.1667 7.8333, -55.9167 7.8333, -55.9167 2.5833, -61.1667 2.5833, -61.1667 7.8333))",
  "dcat_bbox": "ENVELOPE(-61.1667,-55.9167,7.8333,2.5833)",
  "dcat_centroid": "5.2083,-58.5417",
  "pcdm_memberOf_sm": [
    "64bd8c4c-8e60-4956-b43d-bdc3f93db488"
  ],
  "dct_isPartOf_sm": [
    "05d-01",
    "p16022coll230"
  ],
  "dct_rights_sm": [
    "Use of this item may be governed by US and international copyright laws. You may be able to use this item, but copyright and other considerations may apply. For possible additional information or guidance on your use, please contact the contributing organization."
  ],
  "dct_accessRights_s": "Public",
  "dct_format_s": "JPEG",
  "dct_references_s": "{\"http://schema.org/url\":\"https://umedia.lib.umn.edu/item/p16022coll230:2731\",\"http://iiif.io/api/presentation#manifest\":\"https://cdm16022.contentdm.oclc.org/iiif/info/p16022coll230/2731/manifest.json\"}",
  "id": "p16022coll230:2731",
  "dct_identifier_sm": [
    "UMN_ALMA:9938277230001701"
  ],
  "gbl_mdModified_dt": "2022-09-28T02:14:25Z",
  "gbl_mdVersion_s": "Aardvark"
}