{
  "dct_title_s": "Geological map of Hennepin County, Minn",
  "dct_description_sm": [
    "Cartographic Details: Scale not given. Photocopy. \"1876.\"",
    "58 x 49 centimeters",
    "Scale not given.",
    "Minnesota County Maps, Plat Books, and Atlases"
  ],
  "dct_language_sm": [
    "eng"
  ],
  "dct_creator_sm": [
    "Winchell, Newton Horace, 1839-1914"
  ],
  "schema_provider_s": "University of Minnesota",
  "gbl_resourceClass_sm": [
    "Maps"
  ],
  "gbl_resourceType_sm": [
    "Geological maps"
  ],
  "dcat_keyword_sm": [
    "Geology Minnesota Hennepin County Maps",
    "Hennepin County (Minn.) Maps",
    "Maps"
  ],
  "dct_temporal_sm": [
    "1876"
  ],
  "dct_issued_s": "1876",
  "dct_spatial_sm": [
    "Hennepin County, Minnesota",
    "Minnesota"
  ],
  "locn_geometry": "POLYGON((-93.7678 45.2466, -93.1757 45.2466, -93.1757 44.7853, -93.7678 44.7853, -93.7678 45.2466))",
  "dcat_bbox": "ENVELOPE(-93.7678,-93.1757,45.2466,44.7853)",
  "dcat_centroid": "45.015950000000004,-93.47175",
  "pcdm_memberOf_sm": [
    "64bd8c4c-8e60-4956-b43d-bdc3f93db488"
  ],
  "dct_isPartOf_sm": [
    "05d-01",
    "p16022coll231"
  ],
  "dct_rights_sm": [
    "Use of this item may be governed by US and international copyright laws. You may be able to use this item, but copyright and other considerations may apply. For possible additional information or guidance on your use, please contact the contributing organization."
  ],
  "dct_accessRights_s": "Public",
  "dct_format_s": "JPEG",
  "dct_references_s": "{\"http://schema.org/url\":\"https://umedia.lib.umn.edu/item/p16022coll231:57\",\"http://iiif.io/api/presentation#manifest\":\"https://cdm16022.contentdm.oclc.org/iiif/info/p16022coll231/57/manifest.json\"}",
  "id": "p16022coll231:57",
  "dct_identifier_sm": [
    "UMN_ALMA:9949134800001701"
  ],
  "gbl_mdModified_dt": "2022-09-28T02:14:42Z",
  "gbl_mdVersion_s": "Aardvark"
}