{
  "dct_title_s": "Cram's railroad & township map of Minnesota.",
  "dct_description_sm": [
    "Cartographic Details: Scale [1:1,203,840]. 19 miles to an in.Covers northern Iowa, western Wisconsin, and central and southern Minnesota between Cass County and the southern border.Relief shown by hachures.Shows Minnesota counties, cities and towns, railroads, and extent of surveyed townships with Public Land Survey coordinates.At upper right: \"Entered according to Act of Congress in the year 1876, by G.F. Cram, in the Office of the Librarian of Congress at Washington, D.C.\"",
    "52 x 41 centimeters",
    "Scale [1:1,203,840]. 19 miles to an inch",
    "Minnesota Transportation Maps"
  ],
  "dct_language_sm": [
    "eng"
  ],
  "dct_creator_sm": [
    "Cram, George Franklin, 1841-1928"
  ],
  "dct_publisher_sm": [
    "Geo. F. Cram, proprietor of the Western Map Depot  (Chicago, Ill.), 1876"
  ],
  "schema_provider_s": "University of Minnesota",
  "gbl_resourceClass_sm": [
    "Maps"
  ],
  "dcat_keyword_sm": [
    "Railroads Minnesota Maps",
    "Surveying Public Lands Minnesota Maps",
    "Minnesota Maps",
    "Maps",
    "2022-creator-sprint"
  ],
  "dct_temporal_sm": [
    "1877"
  ],
  "dct_issued_s": "1877",
  "gbl_indexYear_im": [
    "1877"
  ],
  "gbl_dateRange_drsim": [
    "[1877 TO 1877]"
  ],
  "dct_spatial_sm": [
    "Minnesota"
  ],
  "locn_geometry": "POLYGON((-96.888 47.688, -90.989 47.688, -90.989 42.936, -96.888 42.936, -96.888 47.688))",
  "dcat_bbox": "ENVELOPE(-96.888,-90.989,47.688,42.936)",
  "dcat_centroid": "45.312,-93.9385",
  "pcdm_memberOf_sm": [
    "64bd8c4c-8e60-4956-b43d-bdc3f93db488"
  ],
  "dct_isPartOf_sm": [
    "05d-01",
    "p16022coll206"
  ],
  "dct_rights_sm": [
    "Use of this item may be governed by US and international copyright laws. You may be able to use this item, but copyright and other considerations may apply. For possible additional information or guidance on your use, please contact the contributing organization."
  ],
  "dct_accessRights_s": "Public",
  "dct_format_s": "JPEG",
  "dct_references_s": "{\"http://iiif.io/api/image\":\"https://cdm16022.contentdm.oclc.org/digital/iiif/p16022coll206/109/info.json\",\"http://schema.org/url\":\"https://umedia.lib.umn.edu/item/p16022coll206:109\",\"http://iiif.io/api/presentation#manifest\":\"https://cdm16022.contentdm.oclc.org/iiif/info/p16022coll206/109/manifest.json\"}",
  "id": "p16022coll206:109",
  "dct_identifier_sm": [
    "UMN_ALMA:9915611370001701"
  ],
  "gbl_mdVersion_s": "Aardvark"
}