{
  "dct_title_s": "Washington and northern Idaho showing lines of the Northern Pacific Ry",
  "dct_description_sm": [
    "Relief shown by hachures and spot heights.; Includes indexes to Northern Pacific stations in Washington and Idaho.; Text describing agricultural opportunities of region and illustrations on verso.; \"No. 41 Form 6317 25M 3-30 MCG-W.\"",
    "46 x 81 centimeters",
    "Scale [approximately 1:1,010,000] not \"one inch = 8 miles\"",
    "General Map Collection"
  ],
  "dct_language_sm": [
    "eng"
  ],
  "dct_creator_sm": [
    "Northern Pacific Railway Company. Agricultural Development Department"
  ],
  "dct_publisher_sm": [
    "McGill-Warner (St. Paul,  Minn)"
  ],
  "schema_provider_s": "University of Minnesota",
  "gbl_resourceClass_sm": [
    "Maps"
  ],
  "dcat_keyword_sm": [
    "Railroads",
    "Railroads"
  ],
  "dct_spatial_sm": [
    "Washington",
    "Idaho"
  ],
  "locn_geometry": "POLYGON((-125.000 49.000, -115.000 49.000, -115.000 45.000, -125.000 45.000, -125.000 49.000))",
  "dcat_bbox": "ENVELOPE(-125.000,-115.000,49.000,45.000)",
  "dcat_centroid": "47.0,-120.0",
  "pcdm_memberOf_sm": [
    "64bd8c4c-8e60-4956-b43d-bdc3f93db488"
  ],
  "dct_isPartOf_sm": [
    "05d-01",
    "p16022coll230"
  ],
  "dct_rights_sm": [
    "Use of this item may be governed by US and international copyright laws. You may be able to use this item, but copyright and other considerations may apply. For possible additional information or guidance on your use, please contact the contributing organization."
  ],
  "dct_accessRights_s": "Public",
  "dct_format_s": "JPEG",
  "dct_references_s": "{\"http://iiif.io/api/image\":\"https://cdm16022.contentdm.oclc.org/digital/iiif/p16022coll230/2395/info.json\",\"http://schema.org/url\":\"https://umedia.lib.umn.edu/item/p16022coll230:2395\",\"http://iiif.io/api/presentation#manifest\":\"https://cdm16022.contentdm.oclc.org/iiif/info/p16022coll230/2395/manifest.json\"}",
  "id": "p16022coll230:2395",
  "dct_identifier_sm": [
    "UMN_ALMA:9974757605001701"
  ],
  "gbl_mdVersion_s": "Aardvark"
}