{
  "dct_title_s": "Dakota",
  "dct_description_sm": [
    "Page number in margin: 52.",
    "52 x 41 centimeters",
    "Scale approximately 1:1,520,640",
    "General Map Collection"
  ],
  "dct_language_sm": [
    "eng"
  ],
  "dct_creator_sm": [
    "Wm. M. Bradley & Bros."
  ],
  "schema_provider_s": "University of Minnesota",
  "gbl_resourceClass_sm": [
    "Maps"
  ],
  "dcat_keyword_sm": [
    "Historical Geography",
    "Dakota Territory Historical Geography Maps",
    "United States Dakota Territory",
    "Maps"
  ],
  "dct_temporal_sm": [
    "1886"
  ],
  "dct_issued_s": "1886",
  "dct_spatial_sm": [
    "North Dakota",
    "South Dakota"
  ],
  "locn_geometry": "POLYGON((-104.05 49.0, -96.55 49.0, -96.55 45.9333, -104.05 45.9333, -104.05 49.0))",
  "dcat_bbox": "ENVELOPE(-104.05,-96.55,49.0,45.9333)",
  "dcat_centroid": "47.46665,-100.3",
  "pcdm_memberOf_sm": [
    "64bd8c4c-8e60-4956-b43d-bdc3f93db488"
  ],
  "dct_isPartOf_sm": [
    "05d-01",
    "p16022coll230"
  ],
  "dct_rights_sm": [
    "Use of this item may be governed by US and international copyright laws. You may be able to use this item, but copyright and other considerations may apply. For possible additional information or guidance on your use, please contact the contributing organization."
  ],
  "dct_accessRights_s": "Public",
  "dct_format_s": "JPEG",
  "dct_references_s": "{\"http://schema.org/url\":\"https://umedia.lib.umn.edu/item/p16022coll230:2077\",\"http://iiif.io/api/presentation#manifest\":\"https://cdm16022.contentdm.oclc.org/iiif/info/p16022coll230/2077/manifest.json\"}",
  "id": "p16022coll230:2077",
  "dct_identifier_sm": [
    "UMN_ALMA:9974117635301701"
  ],
  "gbl_mdModified_dt": "2022-09-28T02:14:48Z",
  "gbl_mdVersion_s": "Aardvark"
}