{
  "dct_title_s": "Political map of Jammu and Kashmir",
  "dct_description_sm": [
    "68 x 92 centimeters",
    "Scale approximately 1:823,680",
    "Ames Library of South Asia Maps"
  ],
  "dct_language_sm": [
    "eng"
  ],
  "dct_creator_sm": [
    "Sarvodaya Service Corporation, New Delhi."
  ],
  "dct_publisher_sm": [
    "S.S. Corporation; New Delhi"
  ],
  "schema_provider_s": "University of Minnesota",
  "gbl_resourceClass_sm": [
    "Maps"
  ],
  "dcat_keyword_sm": [
    "Jammu and Kashmir (India) Administrative and Political Divisions Maps",
    "Jammu and Kashmir (India) Maps",
    "2022-creator-sprint"
  ],
  "dct_temporal_sm": [
    "1957"
  ],
  "dct_issued_s": "1957",
  "gbl_indexYear_im": [
    "1957"
  ],
  "gbl_dateRange_drsim": [
    "[1957 TO 1957]"
  ],
  "dct_spatial_sm": [
    "India--Jammu",
    "India--Kashmir",
    "India"
  ],
  "locn_geometry": "POLYGON((73.750 35.675, 79.461 35.675, 79.461 32.276, 73.750 32.276, 73.750 35.675))",
  "dcat_bbox": "ENVELOPE(73.750,79.461,35.675,32.276)",
  "dcat_centroid": "33.9755,76.6055",
  "pcdm_memberOf_sm": [
    "64bd8c4c-8e60-4956-b43d-bdc3f93db488"
  ],
  "dct_isPartOf_sm": [
    "05d-01",
    "p16022coll246"
  ],
  "dct_rights_sm": [
    "Use of this item may be governed by US and international copyright laws. You may be able to use this item, but copyright and other considerations may apply. For possible additional information or guidance on your use, please contact the contributing organization."
  ],
  "dct_accessRights_s": "Public",
  "dct_format_s": "JPEG",
  "dct_references_s": "{\"http://iiif.io/api/image\":\"https://cdm16022.contentdm.oclc.org/digital/iiif/p16022coll246/374/info.json\",\"http://schema.org/url\":\"https://umedia.lib.umn.edu/item/p16022coll246:374\",\"http://iiif.io/api/presentation#manifest\":\"https://cdm16022.contentdm.oclc.org/iiif/info/p16022coll246/374/manifest.json\"}",
  "id": "p16022coll246:374",
  "dct_identifier_sm": [
    "UMN_ALMA:9974093153701700"
  ],
  "gbl_mdVersion_s": "Aardvark"
}