{
"layer_geom_type_s": "Mixed", 
"layer_modified_dt": "2017-01-20T18:41:03Z", 
"solr_geom": "ENVELOPE(-97.23, -89.53, 49.37, 43.5)", 
"dct_references_s": "{\"http://schema.org/downloadUrl\":\"ftp://ftp.gisdata.mn.gov/pub/gdrs/data/pub/us_mn_state_mngeo/base_saip_photocenters_2009_14/shp_base_saip_photocenters_2009_14.zip\",\"http://schema.org/url\":\"https://gisdata.mn.gov/dataset/base-saip-photocenters-2009-14\",\"http://www.isotc211.org/schemas/2005/gmd/\":\"https://opengeometadata.github.io/edu.umn/e7/d5/c0/dc9b2f492299f7650c2794c2d7/iso19139.xml\"}", 
"dc_rights_s": "Public", 
"uuid": "e7d5c0dc-9b2f-4922-99f7-650c2794c2d7", 
"dct_provenance_s": "Minnesota", 
"dc_subject_sm": [
"Imagery and Base Maps"
], 
"dct_temporal_sm": "2009-2014", 
"dc_description_s": "This dataset contains the center point locations for all images acquired under the Minnesota Spring Aerial Imagery Program from 2009 through 2014. Attributes for each center point include the photo file ID, the center point location, the date of acquisition, and the vendor. Additional attributes for acquisition altitude and camera system are also provided where available.", 
"dct_issued_s": "2015-05-14", 
"dc_format_s": "Shapefile", 
"dc_creator_sm": [
"Minnesota Department of Natural Resources and Minnesota Geospatial Information Office"
], 
"dc_identifier_s": "e7d5c0dc-9b2f-4922-99f7-650c2794c2d7", 
"georss_polygon_s": "43.5 -97.23 49.37 -97.23 49.37 -89.53 43.5 -89.53 43.5 -97.23", 
"solr_year_i": 2009, 
"dct_spatial_sm": [
"Minnesota, United States"
], 
"dc_publisher_sm": [
"Minnesota Department of Natural Resources"
], 
"layer_id_s": "e7d5c0dc-9b2f-4922-99f7-650c2794c2d7", 
"georss_box_s": "43.5 -97.23 49.37 -89.53", 
"dc_title_s": "Aerial Imagery Photo Center Points and Acquisition Dates: Minnesota, Spring 2009-2014", 
"layer_slug_s": "e7d5c0dc-9b2f-4922-99f7-650c2794c2d7", 
"dct_isPartOf_sm": "Minnesota Geospatial Commons"
}