{
"layer_geom_type_s": "Point", 
"layer_modified_dt": "2017-01-20T18:38:58Z", 
"solr_geom": "ENVELOPE(-93.202823, -92.80336, 44.912354, 44.52172)", 
"dct_references_s": "{\"http://schema.org/downloadUrl\":\"ftp://ftp.gisdata.mn.gov/pub/gdrs/data/pub/us_mn_co_dakota/loc_parkrec_parkentrances/shp_loc_parkrec_parkentrances.zip\",\"http://schema.org/url\":\"https://gisdata.mn.gov/dataset/us-mn-co-dakota-loc-parkrec-parkentrances\",\"http://www.isotc211.org/schemas/2005/gmd/\":\"https://opengeometadata.github.io/edu.umn/f6/dc/da/4f572c471ca094577f129d3545/iso19139.xml\"}", 
"dc_rights_s": "Public", 
"uuid": "f6dcda4f-572c-471c-a094-577f129d3545", 
"dct_provenance_s": "Minnesota", 
"dc_subject_sm": [
"Location"
], 
"dct_temporal_sm": "2015", 
"dc_description_s": "Public access locations to Dakota County Parks be it paths or driveways.", 
"dct_issued_s": "2015-09-09", 
"dc_format_s": "Shapefile", 
"dc_creator_sm": [
"Dakota County GIS, Dakota County GIS, Staff"
], 
"dc_identifier_s": "f6dcda4f-572c-471c-a094-577f129d3545", 
"georss_polygon_s": "44.52172 -93.202823 44.912354 -93.202823 44.912354 -92.80336 44.52172 -92.80336 44.52172 -93.202823", 
"solr_year_i": 2015, 
"dct_spatial_sm": [
"Minnesota, United States", 
"Dakota County, Minnesota, United States"
], 
"dc_publisher_sm": [
"Dakota County, Minnesota"
], 
"layer_id_s": "f6dcda4f-572c-471c-a094-577f129d3545", 
"georss_box_s": "44.52172 -93.202823 44.912354 -92.80336", 
"dc_title_s": "Park Entrances: Dakota County, Minnesota, 2015", 
"layer_slug_s": "f6dcda4f-572c-471c-a094-577f129d3545", 
"dct_isPartOf_sm": "Minnesota Geospatial Commons"
}