{
  "dct_title_s": "Geologic map of Minnesota, Two Harbors, bedrock geology",
  "dct_description_sm": [
    "Map showing interpretations of bedrock geology (distribution of rock at the land surface and beneath surface sediments) of the Two Harbors quadrangle, scale 1:250,000."
  ],
  "dct_language_sm": [
    "eng"
  ],
  "dct_creator_sm": [
    "Green, John C., 1932-"
  ],
  "dct_publisher_sm": [
    "Minnesota Geological Survey"
  ],
  "schema_provider_s": "University of Minnesota",
  "gbl_resourceClass_sm": [
    "Maps"
  ],
  "dcat_theme_sm": [
    "Environment"
  ],
  "dct_temporal_sm": [
    "1982"
  ],
  "dct_issued_s": "1982",
  "gbl_indexYear_im": [
    "1982"
  ],
  "gbl_dateRange_drsim": [
    "[1982 TO 1982]"
  ],
  "dct_spatial_sm": [
    "Minnesota"
  ],
  "locn_geometry": "POLYGON((-91.031 48.246, -89.500 48.246, -89.500 47.460, -91.031 47.460, -91.031 48.246))",
  "dcat_bbox": "ENVELOPE(-91.031,-89.500,48.246,47.460)",
  "dcat_centroid": "47.853,-90.2655",
  "pcdm_memberOf_sm": [
    "64bd8c4c-8e60-4956-b43d-bdc3f93db488"
  ],
  "dct_isPartOf_sm": [
    "05d-05"
  ],
  "dct_accessRights_s": "Public",
  "dct_format_s": "PDF",
  "dct_references_s": "{\"http://schema.org/url\":\"https://reflections.mndigital.org/catalog/mgs:772\",\"http://schema.org/downloadUrl\":[{\"url\":\"ftp://mgsftp2.mngs.umn.edu/map_catalog/pdf/umn22372.pdf\",\"label\":\"PDF\"}],\"http://iiif.io/api/image\":\"https://cdm16022.contentdm.oclc.org/digital/iiif/mgs/772/info.json\",\"http://iiif.io/api/presentation#manifest\":\"https://cdm16022.contentdm.oclc.org/iiif/info/mgs/772/manifest.json\"}",
  "id": "46cb0bab-8574-4d80-a568-0ae5f5a78143",
  "dct_identifier_sm": [
    "46cb0bab-8574-4d80-a568-0ae5f5a78143"
  ],
  "gbl_mdVersion_s": "Aardvark"
}