{
  "geoblacklight_version": "1.0",
  "dc_identifier_s": "UMN_ALMA:9976156487701701",
  "dc_rights_s": "Public",
  "dc_title_s": "Septentrionaliora Americae ä Groenlandia, per Freta Davidis et Hudson, ad Terram Novam",
  "dct_provenance_s": "University of Minnesota",
  "layer_slug_s": "p16022coll230:713",
  "solr_geom": "ENVELOPE(-95,-45,83,50)",
  "solr_year_i": "1675",
  "dc_creator_sm": [
    "Wit, Frederick de, 1610-1698"
  ],
  "dc_format_s": "JPEG",
  "dct_references_s": "{\"http://schema.org/downloadUrl\":\"http://cdm16022.contentdm.oclc.org/utils/getfile/collection/p16022coll230/id/713/filename/print/page/download/fparams/forcedownload\",\"http://schema.org/url\":\"https://umedia.lib.umn.edu/item/p16022coll230:713\",\"http://iiif.io/api/presentation#manifest\":\"https://cdm16022.contentdm.oclc.org/iiif/info/p16022coll230/713/manifest.json\"}",
  "dct_spatial_sm": [
    "Canada"
  ],
  "layer_modified_dt": "2022-04-01T15:23:38Z",
  "dc_language_sm": [
    "lat"
  ],
  "dc_publisher_s": "By Frederick de Wit in de Calverstraet by den Dam inde Witte Paskaert (Tot Amsterdam)",
  "dct_issued_s": "1675",
  "dct_temporal_sm": [
    "1675"
  ]
}