{
  "geoblacklight_version": "1.0",
  "dc_identifier_s": "UMN_ALMA:9940540850001701",
  "dc_rights_s": "Public",
  "dc_title_s": "Asia",
  "dct_provenance_s": "University of Minnesota",
  "layer_slug_s": "p16022coll246:178",
  "solr_geom": "ENVELOPE(20.000,170.000,70.000,-10.000)",
  "solr_year_i": "1626",
  "dc_creator_sm": [
    "Speed, John, 1552?-1629"
  ],
  "dc_description_s": "42 x 54 centimeters|Scale approximately 1:18,333,333|Ames Library of South Asia Maps",
  "dc_format_s": "JPEG",
  "dct_references_s": "{\"http://iiif.io/api/image\":\"https://cdm16022.contentdm.oclc.org/digital/iiif/p16022coll246/178/info.json\",\"http://schema.org/url\":\"https://umedia.lib.umn.edu/item/p16022coll246:178\",\"http://iiif.io/api/presentation#manifest\":\"https://cdm16022.contentdm.oclc.org/iiif/info/p16022coll246/178/manifest.json\"}",
  "dct_spatial_sm": [
    "Asia"
  ],
  "dc_language_sm": [
    "eng"
  ],
  "dct_issued_s": "1626",
  "dct_temporal_sm": [
    "1626"
  ]
}