{
  "geoblacklight_version": "1.0",
  "dc_identifier_s": "UMN_ALMA:9973977705101701",
  "dc_rights_s": "Public",
  "dc_title_s": "Map of the Theodore Roosevelt International Highway, Portland, Oregon to Portland, Maine : showing every city, town, village and hamlet throughout its entire length : proposed by the Theodore Roosevelt International Highway Association and also advocated by the National Highways Association, Washington, D.C.",
  "dct_provenance_s": "University of Minnesota",
  "layer_slug_s": "p16022coll230:1226",
  "solr_geom": "ENVELOPE(-125.15,-66.93333333,49.96666667,41.55)",
  "dc_creator_sm": [
    "Mulford, John C"
  ],
  "dc_description_s": "May 1923.; Includes illustrations, notes, and \"Profile of the Theodore Roosevelt International Highway showing elevations above sea level of the principal cities, hotels & garages, and mileage.\"|29 x 126 centimeters, on sheet 46 x 132 centimeters|Scale approximately 1:3,700,000|General Map Collection",
  "dc_format_s": "JPEG",
  "dct_references_s": "{\"http://schema.org/url\":\"https://umedia.lib.umn.edu/item/p16022coll230:1226\",\"http://iiif.io/api/presentation#manifest\":\"https://cdm16022.contentdm.oclc.org/iiif/info/p16022coll230/1226/manifest.json\"}",
  "layer_modified_dt": "2022-09-28T02:16:27Z",
  "dc_language_sm": [
    "eng"
  ],
  "dc_publisher_s": ", 1923",
  "dct_issued_s": "1923"
}