{
  "geoblacklight_version": "1.0",
  "dc_identifier_s": "UMN_ALMA:9975637103801701",
  "dc_rights_s": "Public",
  "dc_title_s": "Karte von dem Königreiche Norwegen",
  "dct_provenance_s": "University of Minnesota",
  "layer_slug_s": "p16022coll230:352",
  "solr_geom": "ENVELOPE(4.32,31.21,71.45,55.09)",
  "dc_creator_sm": [
    "von Reilly, Franz J. J."
  ],
  "dc_description_s": "Cartographic Details: Scale approximately 1:1,500,000 (E 4°03ʹ00ʺ--E 31°21ʹ00ʺ/N 71°18ʹ00ʺ--N 57°48ʹ00ʺ). In lower right: \"Gestochen von Jos. Stöber. XXVIII.\" Inset: Der nördliche Theil des Stifts Drontheim welcher die Aemter Nordland und Finmark enthaelt.|1 map : color ; 72 x 56 centimeters|Scale approximately 1:1,500,000|General Map Collection",
  "dc_format_s": "JPEG",
  "dct_references_s": "{\"http://schema.org/url\":\"https://umedia.lib.umn.edu/item/p16022coll230:352\",\"http://iiif.io/api/presentation#manifest\":\"https://cdm16022.contentdm.oclc.org/iiif/info/p16022coll230/352/manifest.json\"}",
  "dct_spatial_sm": [
    "Norway"
  ],
  "layer_modified_dt": "2022-09-28T02:14:15Z",
  "dc_language_sm": [
    "ger"
  ],
  "dc_publisher_s": "Reilly'sches Landkarten- und Kunstwerke-Verschleiss-Komptoir (Wien), 1796",
  "dct_issued_s": "1796",
  "dct_temporal_sm": [
    "1796"
  ]
}