{
  "geoblacklight_version": "1.0",
  "dc_identifier_s": "UMN_ALMA:9915366360001701",
  "dc_rights_s": "Public",
  "dc_title_s": "Plan del curso de los Rios Huallaga y Ucayali y de la Pampa del Sacramento",
  "dct_provenance_s": "University of Minnesota",
  "layer_slug_s": "p16022coll230:2758",
  "solr_geom": "ENVELOPE(-77.0,-71.0,-4.1667,-12.8333)",
  "solr_year_i": "1851",
  "dc_creator_sm": [
    "Sobreviela, Manuel, -1803"
  ],
  "dc_description_s": "Relief shown by hachures.; \"Senate Ex. Doc. No. 36, 2d Sess., 32d Cong.\"|40 x 27 centimeters|Scale approximately 1:5,000,000|General Map Collection",
  "dc_format_s": "JPEG",
  "dct_references_s": "{\"http://schema.org/url\":\"https://umedia.lib.umn.edu/item/p16022coll230:2758\",\"http://iiif.io/api/presentation#manifest\":\"https://cdm16022.contentdm.oclc.org/iiif/info/p16022coll230/2758/manifest.json\"}",
  "dct_spatial_sm": [
    "South America"
  ],
  "layer_modified_dt": "2023-02-07T18:33:31Z",
  "dc_language_sm": [
    "spa"
  ],
  "dc_publisher_s": "Lith. by A. Hoen & Co (Baltimore,  Md)",
  "dct_issued_s": "1851?",
  "dct_temporal_sm": [
    "1851"
  ]
}